[
  {
    "id": 23,
    "image": "https://i.postimg.cc/DwwBfd7h/IMG-20250330-WA0054.jpg",
    "category": "achievements",
    "title": "Technovus 2025"
  },
  {
    "id": 24,
    "image": "https://i.postimg.cc/GhQX1Swz/IMG-20250329-WA0057.jpg",
    "category": "achievements",
    "title": "Technovus 2025"
  },
  {
    "id": 25,
    "image": "https://i.postimg.cc/hGJsTDJ3/IMG-20250330-WA0064.jpg",
    "category": "achievements",
    "title": "Technovus 2025"
  },
  {
    "id": 26,
    "image": "https://i.postimg.cc/kgYw265b/IMG-20250330-WA0069.jpg",
    "category": "achievements",
    "title": "Technovus 2025"
  },
  {
    "id": 27,
    "image": "https://i.postimg.cc/VN3RFxns/IMG-20250330-WA0075.jpg",
    "category": "achievements",
    "title": "Technovus 2025"
  },
  {
    "id": 28,
    "image": "https://i.postimg.cc/TwgcNtJV/IMG-20250330-WA0087.jpg",
    "category": "achievements",
    "title": "Technovus 2025"
  },
  {
    "id": 29,
    "image": "https://i.postimg.cc/brP971mK/IMG-20250330-WA0130.jpg",
    "category": "achievements",
    "title": "Technovus 2025"
  },
  {
    "id": 30,
    "image": "https://i.postimg.cc/XNK8wDJ3/IMG-20250331-WA0042.jpg",
    "category": "achievements",
    "title": "Technovus 2025"
  },
  {
    "id": 31,
    "image": "https://i.postimg.cc/3JKZ9C4G/IMG-20250331-WA0046.jpg",
    "category": "achievements",
    "title": "Technovus 2025"
  },
  {
    "id": 32,
    "image": "https://i.postimg.cc/X7QkPGdz/IMG-20250401-WA0042.jpg",
    "category": "achievements",
    "title": "Technovus 2025"
  },
  {
    "id": 33,
    "image": "https://i.postimg.cc/qvqxHJGM/Whats-App-Image-2025-08-20-at-10-51-58-2b3294c7.jpg",
    "category": "achievements",
    "title": "Technovus 2025"
  },
  {
    "id": 34,
    "image": "https://i.postimg.cc/FFS6wZHn/Whats-App-Image-2025-08-20-at-13-26-12-cc1eb1ed.jpg",
    "category": "achievements",
    "title": "Pyrokinesis 2025"
  },
  {
    "id": 35,
    "image": "https://i.postimg.cc/FsQ6vLfF/Whats-App-Image-2025-08-20-at-13-26-13-4a02c76a.jpg",
    "category": "achievements",
    "title": "Pyrokinesis 2025"
  },
  {
    "id": 36,
    "image": "https://i.postimg.cc/65LmppRr/Whats-App-Image-2025-08-20-at-13-26-13-d0c6d704.jpg",
    "category": "achievements",
    "title": "Pyrokinesis 2025"
  },
  {
    "id": 37,
    "image": "https://i.postimg.cc/13B2J33m/Screenshot-2025-08-20-095838.png",
    "category": "achievements",
    "title": "Techxetra 2024"
  },
  {
    "id": 38,
    "image": "https://i.postimg.cc/ZKkGqQQS/Screenshot-2025-08-20-095854.png",
    "category": "achievements",
    "title": "Techxetra 2024"
  },
  {
    "id": 39,
    "image": "https://i.postimg.cc/7YgpJVvT/Screenshot-2025-08-20-095921.png",
    "category": "achievements",
    "title": "Techxetra 2024"
  },
  {
    "id": 40,
    "image": "https://i.postimg.cc/fRD1c9Zq/Screenshot-2025-08-20-095940.png",
    "category": "achievements",
    "title": "Techxetra 2024"
  },
  {
    "id": 41,
    "image": "https://i.postimg.cc/J0FS36rb/Whats-App-Image-2025-08-20-at-10-23-44-28d1f3b1.jpg",
    "category": "achievements",
    "title": "Xiworong 2024"
  },
  {
    "id": 42,
    "image": "https://i.postimg.cc/ZRVGnYXs/Whats-App-Image-2025-08-20-at-10-23-47-64c32fc5.jpg",
    "category": "achievements",
    "title": "Xiworong 2024"
  },
  {
    "id": 43,
    "image": "https://i.postimg.cc/0jjLwRsk/Whats-App-Image-2025-08-20-at-10-23-49-731d3d9a.jpg",
    "category": "achievements",
    "title": "Xiworong 2024"
  },
  {
    "id": 44,
    "image": "https://i.postimg.cc/ZKRTr2cy/IMG-20241017-WA0019.jpg",
    "category": "achievements",
    "title": "Prajyukktam 2024"
  },
  {
    "id": 45,
    "image": "https://i.postimg.cc/L5y2c3HX/IMG-20241018-WA0005.jpg",
    "category": "achievements",
    "title": "Prajyukktam 2024"
  },
  {
    "id": 46,
    "image": "https://i.postimg.cc/QNS8Khp3/IMG-20241018-WA0053.jpg",
    "category": "achievements",
    "title": "Prajyukktam 2024"
  },
  {
    "id": 47,
    "image": "https://i.postimg.cc/NfzQbDJC/IMG-20241019-WA0006.jpg",
    "category": "achievements",
    "title": "Prajyukktam 2024"
  },
  {
    "id": 48,
    "image": "https://i.postimg.cc/XYB4P5tj/IMG-20241019-WA0008.jpg",
    "category": "achievements",
    "title": "Prajyukktam 2024"
  },
  {
    "id": 49,
    "image": "https://i.postimg.cc/xdrnVCSK/IMG-20241019-WA0031.jpg",
    "category": "achievements",
    "title": "Prajyukktam 2024"
  },
  {
    "id": 50,
    "image": "https://i.postimg.cc/rpScVk87/IMG-20241019-WA0039.jpg",
    "category": "achievements",
    "title": "Prajyukktam 2024"
  },
  {
    "id": 51,
    "image": "https://i.postimg.cc/G2dR95tt/IMG-20241020-WA0006.jpg",
    "category": "achievements",
    "title": "Prajyukktam 2024"
  },
  {
    "id": 52,
    "image": "https://i.postimg.cc/WzLyYFRy/IMG-20240323-WA0013.jpg",
    "category": "achievements",
    "title": "Phoenix 2024"
  },
  {
    "id": 53,
    "image": "https://i.postimg.cc/J0N2frMz/IMG-20240323-WA0025.jpg",
    "category": "achievements",
    "title": "Phoenix 2024"
  },
  {
    "id": 54,
    "image": "https://i.postimg.cc/fRTrPQFM/IMG-20240323-WA0026.jpg",
    "category": "achievements",
    "title": "Phoenix 2024"
  },
  {
    "id": 55,
    "image": "https://i.postimg.cc/wTkrFjwW/IMG-20240323-WA0033.jpg",
    "category": "achievements",
    "title": "Phoenix 2024"
  },
  {
    "id": 56,
    "image": "https://i.postimg.cc/XYHzSDSd/IMG-20240324-WA0003.jpg",
    "category": "achievements",
    "title": "Phoenix 2024"
  },
  {
    "id": 57,
    "image": "https://i.postimg.cc/N0KPg7BV/IMG-20240324-WA0005.jpg",
    "category": "achievements",
    "title": "Phoenix 2024"
  },
  {
    "id": 58,
    "image": "https://i.postimg.cc/wMQwWwQt/IMG-20240324-WA0007.jpg",
    "category": "achievements",
    "title": "Phoenix 2024"
  },
  {
    "id": 59,
    "image": "https://i.postimg.cc/QMvYV9MM/IMG-20240324-WA0021.jpg",
    "category": "achievements",
    "title": "Phoenix 2024"
  },
  {
    "id": 60,
    "image": "https://i.postimg.cc/7hkBMF08/IMG-20240324-WA0022.jpg",
    "category": "achievements",
    "title": "Phoenix 2024"
  },
  {
    "id": 61,
    "image": "https://i.postimg.cc/d1dHCs7j/IMG-20240325-WA0045.jpg",
    "category": "achievements",
    "title": "Phoenix 2024"
  },
  {
    "id": 62,
    "image": "https://i.postimg.cc/mZYp2rWb/IMG20240323143958.jpg",
    "category": "achievements",
    "title": "Phoenix 2024"
  },
  {
    "id": 63,
    "image": "https://i.postimg.cc/8PwyMnC9/IMG20240323144546.jpg",
    "category": "achievements",
    "title": "Phoenix 2024"
  },
  {
    "id": 64,
    "image": "https://i.postimg.cc/Yqtn4wtQ/IMG20240323144550.jpg",
    "category": "achievements",
    "title": "Phoenix 2024"
  },
  {
    "id": 65,
    "image": "https://i.postimg.cc/NGmS94mv/IMG-9446.jpg",
    "category": "achievements",
    "title": "Phoenix 2024"
  },
  {
    "id": 66,
    "image": "https://i.postimg.cc/15STpqrn/IMG-9456.jpg",
    "category": "achievements",
    "title": "Phoenix 2024"
  },
  {
    "id": 67,
    "image": "https://i.postimg.cc/rs4kK2TB/Whats-App-Image-2024-09-14-at-13-26-23-85dcf28f.jpg",
    "category": "achievements",
    "title": "Kshitij 2024"
  },
  {
    "id": 68,
    "image": "https://i.postimg.cc/tRnyrW6B/Whats-App-Image-2024-09-14-at-13-26-23-a7972e86.jpg",
    "category": "achievements",
    "title": "Kshitij 2024"
  },
  {
    "id": 69,
    "image": "https://i.postimg.cc/bvrdr42g/IMG-20231103-WA0011.jpg",
    "category": "achievements",
    "title": "Xiworong 2023"
  },
  {
    "id": 70,
    "image": "https://i.postimg.cc/k5HGbwQm/IMG-20231103-WA0026.jpg",
    "category": "achievements",
    "title": "Xiworong 2023"
  },
  {
    "id": 71,
    "image": "https://i.postimg.cc/26B6FvGB/IMG-20231103-WA0027.jpg",
    "category": "achievements",
    "title": "Xiworong 2023"
  },
  {
    "id": 72,
    "image": "https://i.postimg.cc/9QJrWczz/IMG-20231103-WA0034.jpg",
    "category": "achievements",
    "title": "Xiworong 2023"
  },
  {
    "id": 73,
    "image": "https://i.postimg.cc/j20j8533/IMG-20231103-WA0038.jpg",
    "category": "achievements",
    "title": "Xiworong 2023"
  },
  {
    "id": 74,
    "image": "https://i.postimg.cc/dQr3h2Db/IMG-20231103-WA0039.jpg",
    "category": "achievements",
    "title": "Xiworong 2023"
  },
  {
    "id": 75,
    "image": "https://i.postimg.cc/qqsvWT9J/IMG-20231104-WA0001.jpg",
    "category": "achievements",
    "title": "Xiworong 2023"
  },
  {
    "id": 76,
    "image": "https://i.postimg.cc/G2bYXXBs/IMG-20231012-WA0025.jpg",
    "category": "achievements",
    "title": "Technophilia 3.0 2023"
  },
  {
    "id": 77,
    "image": "https://i.postimg.cc/J0nXLt5r/IMG-20231012-WA0026.jpg",
    "category": "achievements",
    "title": "Technophilia 3.0 2023"
  },
  {
    "id": 78,
    "image": "https://i.postimg.cc/rp1xGBpk/IMG-20231012-WA0029.jpg",
    "category": "achievements",
    "title": "Technophilia 3.0 2023"
  },
  {
    "id": 79,
    "image": "https://i.postimg.cc/26TWMnv9/IMG-20231012-WA0030.jpg",
    "category": "achievements",
    "title": "Technophilia 3.0 2023"
  },
  {
    "id": 80,
    "image": "https://i.postimg.cc/90n7FVLG/IMG-20231012-WA0078.jpg",
    "category": "achievements",
    "title": "Technophilia 3.0 2023"
  },
  {
    "id": 81,
    "image": "https://i.postimg.cc/2jcvxFCV/IMG-20231013-WA0003.jpg",
    "category": "achievements",
    "title": "Technophilia 3.0 2023"
  },
  {
    "id": 82,
    "image": "https://i.postimg.cc/pXmjchdk/IMG-20231013-WA0004.jpg",
    "category": "achievements",
    "title": "Technophilia 3.0 2023"
  },
  {
    "id": 83,
    "image": "https://i.postimg.cc/65FvkW2K/IMG-20231013-WA0038.jpg",
    "category": "achievements",
    "title": "Technophilia 3.0 2023"
  },
  {
    "id": 84,
    "image": "https://i.postimg.cc/ZntkkyS3/wrc.jpg",
    "category": "achievements",
    "title": "Technoxian 7.0 World Robotics Championship 2023"
  },
  {
    "id": 85,
    "image": "https://i.postimg.cc/FRJtnV2N/wrc2.jpg",
    "category": "achievements",
    "title": "Technoxian 7.0 World Robotics Championship 2023"
  },
  {
    "id": 86,
    "image": "https://i.postimg.cc/xdZDR4p6/wrc2023.jpg",
    "category": "achievements",
    "title": "Technoxian 7.0 World Robotics Championship 2023"
  },
  {
    "id": 87,
    "image": "https://i.postimg.cc/L41RympL/techkriti1.jpg",
    "category": "achievements",
    "title": "Techkriti 2023"
  },
  {
    "id": 88,
    "image": "https://i.postimg.cc/cCwS6BmX/techkriti2.jpg",
    "category": "achievements",
    "title": "Techkriti 2023"
  },
  {
    "id": 89,
    "image": "https://i.postimg.cc/mgWvp9wG/kshitij1.jpg",
    "category": "achievements",
    "title": "Kshitij 2023"
  },
  {
    "id": 90,
    "image": "https://i.postimg.cc/9M0KwYWy/kshitij2.jpg",
    "category": "achievements",
    "title": "Kshitij 2023"
  },
  {
    "id": 91,
    "image": "https://i.postimg.cc/sgPtk26G/kshitij3.jpg",
    "category": "achievements",
    "title": "Kshitij 2023"
  },
  {
    "id": 92,
    "image": "https://i.postimg.cc/Jh19MWv6/kshitij4.jpg",
    "category": "achievements",
    "title": "Kshitij 2023"
  },
  {
    "id": 93,
    "image": "https://i.postimg.cc/DzBRzMK2/kshitij6.jpg",
    "category": "achievements",
    "title": "Kshitij 2023"
  },
  {
    "id": 94,
    "image": "https://i.postimg.cc/0jB8JNRy/technoesis.jpg",
    "category": "achievements",
    "title": "Tecnoesis 2022"
  },
  {
    "id": 96,
    "image": "https://i.postimg.cc/DwDXK2SF/sih2022.jpg",
    "category": "achievements",
    "title": "Smart India Hackathon 2022"
  },
  {
    "id": 97,
    "image": "https://i.postimg.cc/fbtY3VGJ/wrc.jpg",
    "category": "achievements",
    "title": "Technoxian 6.0 World Cup 2022"
  },
  {
    "id": 98,
    "image": "https://i.postimg.cc/Jzdb4Ndf/wrc-2022.jpg",
    "category": "achievements",
    "title": "Technoxian 6.0 World Cup 2022"
  },
  {
    "id": 99,
    "image": "https://i.postimg.cc/3x3GZLP5/techtoy1.jpg",
    "category": "achievements",
    "title": "Tech Toy 2020 Hackathon"
  },
  {
    "id": 100,
    "image": "https://i.postimg.cc/9Q17gdh4/techtoy2.jpg",
    "category": "achievements",
    "title": "Tech Toy 2020 Hackathon"
  },
  {
    "id": 101,
    "image": "https://i.postimg.cc/hjB7ZpYq/sih1.jpg",
    "category": "achievements",
    "title": "Smart India Hackathon 2019"
  },
  {
    "id": 102,
    "image": "https://i.postimg.cc/mrMHS08w/sih2.jpg",
    "category": "achievements",
    "title": "Smart India Hackathon 2019"
  },
  {
    "id": 103,
    "image": "https://i.postimg.cc/R0RM9dFm/supernerds1.jpg",
    "category": "achievements",
    "title": "SUPERNERDS 2019"
  },
  {
    "id": 104,
    "image": "https://i.postimg.cc/Qdc8YhZH/supernerds2.jpg",
    "category": "achievements",
    "title": "SUPERNERDS 2019"
  },
  {
    "id": 105,
    "image": "https://i.postimg.cc/mrRb0JTV/supernerds3.jpg",
    "category": "achievements",
    "title": "SUPERNERDS 2019"
  },
  {
    "id": 106,
    "image": "https://i.postimg.cc/XvznpJw1/Screenshot-2025-08-23-220712.png",
    "category": "achievements",
    "title": "Abeyaantrix 2018"
  },
  {
    "id": 107,
    "image": "https://i.postimg.cc/XJB4FbLj/Screenshot-2025-08-23-220722.png",
    "category": "achievements",
    "title": "Abeyaantrix 2018"
  },
  {
    "id": 108,
    "image": "https://i.postimg.cc/x8rY34pK/Screenshot-2025-08-23-220732.png",
    "category": "achievements",
    "title": "Abeyaantrix 2018"
  },
  {
    "id": 109,
    "image": "https://i.postimg.cc/k54nJ8tt/Screenshot-2025-08-23-220740.png",
    "category": "achievements",
    "title": "Abeyaantrix 2018"
  },
  {
    "id": 110,
    "image": "https://i.postimg.cc/J7JRzRtK/Screenshot-2025-08-23-220749.png",
    "category": "achievements",
    "title": "Abeyaantrix 2018"
  },
  {
    "id": 111,
    "image": "https://i.postimg.cc/zXr8L4gN/Screenshot-2025-08-23-220756.png",
    "category": "achievements",
    "title": "Abeyaantrix 2018"
  },
  {
    "id": 112,
    "image": "https://i.postimg.cc/6qZg660Z/hpv1.jpg",
    "category": "achievements",
    "title": "Human Powered Vehicle Competition 2018"
  },
  {
    "id": 113,
    "image": "https://i.postimg.cc/pXN3G8WJ/hpv2.jpg",
    "category": "achievements",
    "title": "Human Powered Vehicle Competition 2018"
  },
  {
    "id": 114,
    "image": "https://i.postimg.cc/Df4tP5Tz/hpv3.jpg",
    "category": "achievements",
    "title": "Human Powered Vehicle Competition 2018"
  },
  {
    "id": 115,
    "image": "https://i.postimg.cc/Jnc2DYX6/techxetra1.jpg",
    "category": "achievements",
    "title": "Techxetra 2016"
  },
  {
    "id": 116,
    "image": "https://i.postimg.cc/9MjkfHDw/techxetra2.jpg",
    "category": "achievements",
    "title": "Techxetra 2016"
  },
  {
    "id": 117,
    "image": "https://i.postimg.cc/VvfHj9BY/techxetra3.jpg",
    "category": "achievements",
    "title": "Techxetra 2016"
  },
  {
    "id": 118,
    "image": "https://i.postimg.cc/Sxxky8Bb/auxesis-2.jpg",
    "category": "achievements",
    "title": "Auxesis 2016"
  },
  {
    "id": 119,
    "image": "https://i.postimg.cc/7ZtDbh4G/auxesis-2016.jpg",
    "category": "achievements",
    "title": "Auxesis 2016"
  },
  {
    "id": 120,
    "image": "https://i.postimg.cc/5tZVqr6f/auxesis3.jpg",
    "category": "achievements",
    "title": "Auxesis 2016"
  },
  {
    "id": 121,
    "image": "https://i.postimg.cc/8CFGvGky/auxesis4.jpg",
    "category": "achievements",
    "title": "Auxesis 2016"
  },
  {
    "id": 122,
    "image": "https://i.postimg.cc/SNvDsYRz/Whats-App-Image-2025-08-23-at-23-25-29-2671ac14.jpg",
    "category": "events",
    "title": "Robo Soccer 2025"
  },
  {
    "id": 123,
    "image": "https://i.postimg.cc/FKtpbtjr/Whats-App-Image-2025-08-23-at-23-25-30-22c8b8ee.jpg",
    "category": "events",
    "title": "Robo Soccer 2025"
  },
  {
    "id": 124,
    "image": "https://i.postimg.cc/BnPN1ZP7/Whats-App-Image-2025-08-23-at-23-25-30-f03628bd.jpg",
    "category": "events",
    "title": "Robo Soccer 2025"
  },
  {
    "id": 125,
    "image": "https://i.postimg.cc/KYnNJ9Nn/Whats-App-Image-2025-08-23-at-23-25-31-1ee3a5b2.jpg",
    "category": "events",
    "title": "Robo Soccer 2025"
  },
  {
    "id": 126,
    "image": "https://i.postimg.cc/ZRHLhCXn/Whats-App-Image-2025-08-23-at-23-25-32-e02b9838.jpg",
    "category": "events",
    "title": "Robo Soccer 2025"
  },
  {
    "id": 127,
    "image": "https://i.postimg.cc/1XYcfbmZ/Whats-App-Image-2025-08-23-at-23-25-33-81dc6478.jpg",
    "category": "events",
    "title": "Robo Soccer 2025"
  },
  {
    "id": 128,
    "image": "https://i.postimg.cc/gj0HcGPD/Whats-App-Image-2025-08-23-at-23-25-33-ccebc1a9.jpg",
    "category": "events",
    "title": "Robo Soccer 2025"
  },
  {
    "id": 129,
    "image": "https://i.postimg.cc/L4yVCgz0/Whats-App-Image-2025-08-23-at-23-25-34-00b4a0ac.jpg",
    "category": "events",
    "title": "Robo Soccer 2025"
  },
  {
    "id": 130,
    "image": "https://i.postimg.cc/BQkBsW7T/Whats-App-Image-2025-08-23-at-23-25-34-270cbbc2.jpg",
    "category": "events",
    "title": "Robo Soccer 2025"
  },
  {
    "id": 131,
    "image": "https://i.postimg.cc/gknHfcsc/Whats-App-Image-2025-08-23-at-23-26-46-78e1edd7.jpg",
    "category": "events",
    "title": "Robo Soccer 2025"
  },
  {
    "id": 132,
    "image": "https://i.postimg.cc/T2mRQnMT/Whats-App-Image-2025-08-23-at-23-23-14-e8b76d55.jpg",
    "category": "events",
    "title": "Robo Race 2025"
  },
  {
    "id": 133,
    "image": "https://i.postimg.cc/VLWzP1kT/Whats-App-Image-2025-08-23-at-23-23-15-34594ec9.jpg",
    "category": "events",
    "title": "Robo Race 2025"
  },
  {
    "id": 134,
    "image": "https://i.postimg.cc/3xrYK6yw/Whats-App-Image-2025-08-23-at-23-23-16-4c4fdafc.jpg",
    "category": "events",
    "title": "Robo Race 2025"
  },
  {
    "id": 135,
    "image": "https://i.postimg.cc/YqHtPjMY/Whats-App-Image-2025-08-23-at-23-23-16-5a789b7c.jpg",
    "category": "events",
    "title": "Robo Race 2025"
  },
  {
    "id": 136,
    "image": "https://i.postimg.cc/3Rkw3qcG/Whats-App-Image-2025-08-23-at-23-18-00-2c2523c4.jpg",
    "category": "events",
    "title": "Pick n Place Challenge"
  },
  {
    "id": 137,
    "image": "https://i.postimg.cc/SsHxRGBv/Whats-App-Image-2025-08-23-at-23-18-02-497d448f.jpg",
    "category": "events",
    "title": "Pick n Place Challenge"
  },
  {
    "id": 138,
    "image": "https://i.postimg.cc/Zq7RtmVZ/Whats-App-Image-2025-08-23-at-23-18-04-7bcc9653.jpg",
    "category": "events",
    "title": "Pick n Place Challenge"
  },
  {
    "id": 139,
    "image": "https://i.postimg.cc/FzcsLLms/Whats-App-Image-2025-08-23-at-23-18-06-30c3dada.jpg",
    "category": "events",
    "title": "Pick n Place Challenge"
  },
  {
    "id": 140,
    "image": "https://i.postimg.cc/66GQSDRJ/Whats-App-Image-2025-08-23-at-23-18-08-34d041ce.jpg",
    "category": "events",
    "title": "Pick n Place Challenge"
  },
  {
    "id": 141,
    "image": "https://i.postimg.cc/28R5f2Fq/Whats-App-Image-2025-08-23-at-23-18-08-f26ff048.jpg",
    "category": "events",
    "title": "Pick n Place Challenge"
  },
  {
    "id": 142,
    "image": "https://i.postimg.cc/xdS8ygqD/IMG-20250820-WA0003.jpg",
    "category": "events",
    "title": "RoboRace Workshop"
  },
  {
    "id": 143,
    "image": "https://i.postimg.cc/TPqwkmWy/IMG-20250820-WA0004.jpg",
    "category": "events",
    "title": "RoboRace Workshop"
  },
  {
    "id": 144,
    "image": "https://i.postimg.cc/504tD0ws/IMG-20250820-WA0005.jpg",
    "category": "events",
    "title": "RoboRace Workshop"
  },
  {
    "id": 145,
    "image": "https://i.postimg.cc/RZtqH2SL/IMG-20250820-WA0006.jpg",
    "category": "events",
    "title": "RoboRace Workshop"
  },
  {
    "id": 146,
    "image": "https://i.postimg.cc/J0tz42YJ/IMG-20250820-WA0007.jpg",
    "category": "events",
    "title": "RoboRace Workshop"
  },
  {
    "id": 147,
    "image": "https://i.postimg.cc/Tw6b1fnb/Whats-App-Image-2025-02-21-at-22-40-58-4134b255.jpg",
    "category": "events",
    "title": "Robotic Arm Making Workshop"
  },
  {
    "id": 148,
    "image": "https://i.postimg.cc/LX31ZwVb/Whats-App-Image-2025-02-21-at-22-40-58-c71744b3.jpg",
    "category": "events",
    "title": "Robotic Arm Making Workshop"
  },
  {
    "id": 149,
    "image": "https://i.postimg.cc/6q6GVcj5/Whats-App-Image-2025-02-21-at-22-40-59-432df006.jpg",
    "category": "events",
    "title": "Robotic Arm Making Workshop"
  },
  {
    "id": 150,
    "image": "https://i.postimg.cc/R0ffvNJ9/Whats-App-Image-2025-02-21-at-22-40-59-59da65c8.jpg",
    "category": "events",
    "title": "Robotic Arm Making Workshop"
  },
  {
    "id": 151,
    "image": "https://i.postimg.cc/D0C4xGHQ/Whats-App-Image-2025-02-21-at-22-40-59-a05e55b6.jpg",
    "category": "events",
    "title": "Robotic Arm Making Workshop"
  },
  {
    "id": 152,
    "image": "https://i.postimg.cc/WbF1Bxkc/Whats-App-Image-2025-08-20-at-10-51-57-3caa0017.jpg",
    "category": "events",
    "title": "Robotic Arm Making Workshop"
  },
  {
    "id": 153,
    "image": "https://i.postimg.cc/tJDW8wZx/Whats-App-Image-2025-08-23-at-23-02-47-19d81d48.jpg",
    "category": "events",
    "title": "Bottle Rocket Launch"
  },
  {
    "id": 154,
    "image": "https://i.postimg.cc/D071jnZh/Whats-App-Image-2025-08-23-at-23-02-47-3013627e.jpg",
    "category": "events",
    "title": "Bottle Rocket Launch"
  },
  {
    "id": 155,
    "image": "https://i.postimg.cc/vBrWtcGX/Whats-App-Image-2025-08-23-at-23-02-47-98e513bf.jpg",
    "category": "events",
    "title": "Bottle Rocket Launch"
  },
  {
    "id": 156,
    "image": "https://i.postimg.cc/Yqq1QrZf/Whats-App-Image-2025-08-23-at-23-02-48-376563e2.jpg",
    "category": "events",
    "title": "Bottle Rocket Launch"
  },
  {
    "id": 157,
    "image": "https://i.postimg.cc/2jxQqbcS/Whats-App-Image-2025-08-23-at-23-02-48-479c8580.jpg",
    "category": "events",
    "title": "Bottle Rocket Launch"
  },
  {
    "id": 158,
    "image": "https://i.postimg.cc/m2X7jxGx/Whats-App-Image-2025-08-23-at-23-02-49-85fc1925.jpg",
    "category": "events",
    "title": "Bottle Rocket Launch"
  },
  {
    "id": 159,
    "image": "https://i.postimg.cc/3R7SgMgM/Whats-App-Image-2025-02-21-at-22-44-50-18722080.jpg",
    "category": "events",
    "title": "Bot Show 2024"
  },
  {
    "id": 160,
    "image": "https://i.postimg.cc/YC5yCL0C/Whats-App-Image-2025-02-21-at-22-45-13-b19e71d1.jpg",
    "category": "events",
    "title": "Bot Show 2024"
  },
  {
    "id": 161,
    "image": "https://i.postimg.cc/TPnNL25q/Whats-App-Image-2025-02-21-at-22-45-45-cde42645.jpg",
    "category": "events",
    "title": "Bot Show 2024"
  },
  {
    "id": 162,
    "image": "https://i.postimg.cc/gjtgFn1d/Whats-App-Image-2025-02-21-at-22-45-46-38ef2a94.jpg",
    "category": "events",
    "title": "Bot Show 2024"
  },
  {
    "id": 163,
    "image": "https://i.postimg.cc/VvvFRzvh/Whats-App-Image-2025-02-21-at-22-45-49-e2b5e098.jpg",
    "category": "events",
    "title": "Bot Show 2024"
  },
  {
    "id": 164,
    "image": "https://i.postimg.cc/FsQR3D6y/IMG-20240324-WA0023.jpg",
    "category": "events",
    "title": "Robo Soccer 2024"
  },
  {
    "id": 165,
    "image": "https://i.postimg.cc/Tw4dKcDD/IMG-20240324-WA0028.jpg",
    "category": "events",
    "title": "Robo Race 2024"
  },
  {
    "id": 166,
    "image": "https://i.postimg.cc/nr9HBQ4w/IMG-9441.jpg",
    "category": "events",
    "title": "Robo Race 2024"
  },
  {
    "id": 167,
    "image": "https://i.postimg.cc/QttNNzHD/IMG-20240323-WA0017.jpg",
    "category": "events",
    "title": "Rowboat Race 2024"
  },
  {
    "id": 168,
    "image": "https://i.postimg.cc/vB7MXvJk/aytc1.jpg",
    "category": "events",
    "title": "Arnab Kishor Bordoloi Young Technovator Competition 2021"
  },
  {
    "id": 169,
    "image": "https://i.postimg.cc/K8VZYj7q/aytc2.jpg",
    "category": "events",
    "title": "Arnab Kishor Bordoloi Young Technovator Competition 2021"
  },
  {
    "id": 170,
    "image": "https://i.postimg.cc/1t1spdjD/aytc3.jpg",
    "category": "events",
    "title": "Arnab Kishor Bordoloi Young Technovator Competition 2021"
  },
  {
    "id": 171,
    "image": "https://i.postimg.cc/XvCnBWQV/aytc4.jpg",
    "category": "events",
    "title": "Arnab Kishor Bordoloi Young Technovator Competition 2021"
  },
  {
    "id": 172,
    "image": "https://i.postimg.cc/SRy4PMqs/aytc5.jpg",
    "category": "events",
    "title": "Arnab Kishor Bordoloi Young Technovator Competition 2021"
  },
  {
    "id": 173,
    "image": "https://i.postimg.cc/90J2HQFB/aytc6.jpg",
    "category": "events",
    "title": "Arnab Kishor Bordoloi Young Technovator Competition 2021"
  },
  {
    "id": 174,
    "image": "https://i.postimg.cc/5ytyDGqD/technosphere1.jpg",
    "category": "events",
    "title": "Technosphere 2019"
  },
  {
    "id": 175,
    "image": "https://i.postimg.cc/XvVb25gz/technos1.jpg",
    "category": "events",
    "title": "Technosphere 2019"
  },
  {
    "id": 176,
    "image": "https://i.postimg.cc/HkmngV2Q/technos10.jpg",
    "category": "events",
    "title": "Technosphere 2019"
  },
  {
    "id": 177,
    "image": "https://i.postimg.cc/Jz38cxjX/technos2.jpg",
    "category": "events",
    "title": "Technosphere 2019"
  },
  {
    "id": 178,
    "image": "https://i.postimg.cc/FKDQwKWs/technos3.jpg",
    "category": "events",
    "title": "Technosphere 2019"
  },
  {
    "id": 179,
    "image": "https://i.postimg.cc/pTrtvt4Q/technos4.jpg",
    "category": "events",
    "title": "Technosphere 2019"
  },
  {
    "id": 180,
    "image": "https://i.postimg.cc/52W1CTQ1/technos4-1.jpg",
    "category": "events",
    "title": "Technosphere 2019"
  },
  {
    "id": 181,
    "image": "https://i.postimg.cc/zBQYXcYs/technos5.jpg",
    "category": "events",
    "title": "Technosphere 2019"
  },
  {
    "id": 182,
    "image": "https://i.postimg.cc/6qGJ7f9y/technos6.jpg",
    "category": "events",
    "title": "Technosphere 2019"
  },
  {
    "id": 183,
    "image": "https://i.postimg.cc/t7Q0FnTD/technos7.jpg",
    "category": "events",
    "title": "Technosphere 2019"
  },
  {
    "id": 184,
    "image": "https://i.postimg.cc/BZ8XcWb1/technos8.jpg",
    "category": "events",
    "title": "Technosphere 2019"
  },
  {
    "id": 185,
    "image": "https://i.postimg.cc/X7dqmwwj/technos9.jpg",
    "category": "events",
    "title": "Technosphere 2019"
  },
  {
    "id": 186,
    "image": "https://i.postimg.cc/9XvzLxwg/technos9-1.jpg",
    "category": "events",
    "title": "Technosphere 2019"
  },
  {
    "id": 187,
    "image": "https://i.postimg.cc/8zM9gC5g/byot1.jpg",
    "category": "events",
    "title": "BYOT 2018"
  },
  {
    "id": 188,
    "image": "https://i.postimg.cc/R0m8Sz66/byot2.jpg",
    "category": "events",
    "title": "BYOT 2018"
  },
  {
    "id": 189,
    "image": "https://i.postimg.cc/0NC4rHDt/byot3.jpg",
    "category": "events",
    "title": "BYOT 2018"
  },
  {
    "id": 190,
    "image": "https://i.postimg.cc/cH4b3Mcd/byot4.jpg",
    "category": "events",
    "title": "BYOT 2018"
  },
  {
    "id": 191,
    "image": "https://i.postimg.cc/d3gHzMc0/byot5.jpg",
    "category": "events",
    "title": "BYOT 2018"
  },
  {
    "id": 192,
    "image": "https://i.postimg.cc/3RSbF4Lm/byot6.jpg",
    "category": "events",
    "title": "BYOT 2018"
  },
  {
    "id": 193,
    "image": "https://i.postimg.cc/mkPpXLqq/byot7.jpg",
    "category": "events",
    "title": "BYOT 2018"
  },
  {
    "id": 194,
    "image": "https://i.postimg.cc/nc70CPtv/webinar1.jpg",
    "category": "events",
    "title": "Webinar Series on Engineers Day 2017"
  },
  {
    "id": 195,
    "image": "https://i.postimg.cc/fRfCvSyy/webinar2.jpg",
    "category": "events",
    "title": "Webinar Series on Engineers Day 2017"
  },
  {
    "id": 196,
    "image": "https://i.postimg.cc/Hkg359pF/webinar3.jpg",
    "category": "events",
    "title": "Webinar Series on Engineers Day 2017"
  },
  {
    "id": 197,
    "image": "https://i.postimg.cc/qBW1BdWJ/webinar4.jpg",
    "category": "events",
    "title": "Webinar Series on Engineers Day 2017"
  },
  {
    "id": 198,
    "image": "https://i.postimg.cc/Dzfgpf4g/webinar5.jpg",
    "category": "events",
    "title": "Webinar Series on Engineers Day 2017"
  }
]